socketfromfd.py
socketfromfd-0.2.0.dist-info/DESCRIPTION.rst
socketfromfd-0.2.0.dist-info/METADATA
socketfromfd-0.2.0.dist-info/RECORD
socketfromfd-0.2.0.dist-info/WHEEL
socketfromfd-0.2.0.dist-info/metadata.json
socketfromfd-0.2.0.dist-info/top_level.txt
